eclipsegen_cli/__init__.py
eclipsegen_cli/cmd.py
eclipsegen_cli/main.py
eclipsegen_cli-0.2.7.dist-info/LICENSE
eclipsegen_cli-0.2.7.dist-info/METADATA
eclipsegen_cli-0.2.7.dist-info/NOTICE
eclipsegen_cli-0.2.7.dist-info/WHEEL
eclipsegen_cli-0.2.7.dist-info/entry_points.txt
eclipsegen_cli-0.2.7.dist-info/top_level.txt
eclipsegen_cli-0.2.7.dist-info/RECORD
