Metadata-Version: 2.1
Name: eclipsegen-cli
Version: 0.2.7
Summary: Generate Eclipse instances from a single command-line call
Home-page: http://github.com/Gohla/eclipsegen_cli
Author: Gabriel Konat
Author-email: gabrielkonat@gmail.com
License: Apache 2.0
Platform: UNKNOWN
Requires-Dist: eclipsegen (==0.4.5)
Requires-Dist: plumbum (>=1.6.2)
